phaeton-0.2.3.dist-info/METADATA
phaeton-0.2.3.dist-info/WHEEL
phaeton-0.2.3.dist-info/licenses/LICENSE
phaeton/__init__.py
phaeton/_internal.py
phaeton/_phaeton.pyd
phaeton/engine.py
phaeton/pipeline.py
phaeton-0.2.3.dist-info/RECORD
