Metadata-Version: 2.4
Name: phaeton
Version: 0.2.3
Classifier: Development Status :: 4 - Beta
Classifier: Intended Audience :: Developers
Classifier: Intended Audience :: Science/Research
Classifier: License :: OSI Approved :: MIT License
Classifier: Programming Language :: Rust
Classifier: Programming Language :: Python :: Implementation :: CPython
Classifier: Programming Language :: Python :: 3.8
Classifier: Programming Language :: Python :: 3.9
Classifier: Programming Language :: Python :: 3.10
Classifier: Programming Language :: Python :: 3.11
Classifier: Programming Language :: Python :: 3.12
Classifier: Programming Language :: Python :: 3.13
Classifier: Topic :: Software Development :: Libraries :: Python Modules
Classifier: Topic :: Scientific/Engineering :: Information Analysis
Requires-Dist: pytest>=7.0 ; extra == 'dev'
Requires-Dist: maturin>=1.0 ; extra == 'dev'
Requires-Dist: faker>=19.0 ; extra == 'dev'
Provides-Extra: dev
License-File: LICENSE
Summary: A high-performance preprocessing and ETL engine for sanitizing raw data streams, accelerated by Rust.
Keywords: data-cleaning,rust,preprocessing,etl,high-performance,streaming
Author-email: Zahraan Dzakii Tsaqiif <zahraandzakiits@gmail.com>
Requires-Python: >=3.8
Project-URL: Homepage, https://github.com/rannd1nt/phaeton
Project-URL: Repository, https://github.com/rannd1nt/phaeton
Project-URL: Issues, https://github.com/rannd1nt/phaeton/issues
Project-URL: Documentation, https://github.com/rannd1nt/phaeton#readme
